{
  "routes": [
    {
      "method": "GET",
      "path": "/perks",
      "handler": "perk.find",
      "config": {
        "policies": []
      }
    },
    {
      "method": "GET",
      "path": "/perks/count",
      "handler": "perk.count",
      "config": {
        "policies": []
      }
    },
    {
      "method": "GET",
      "path": "/perks/:id",
      "handler": "perk.findOne",
      "config": {
        "policies": []
      }
    },
    {
      "method": "POST",
      "path": "/perks",
      "handler": "perk.create",
      "config": {
        "policies": []
      }
    },
    {
      "method": "PUT",
      "path": "/perks/:id",
      "handler": "perk.update",
      "config": {
        "policies": []
      }
    },
    {
      "method": "DELETE",
      "path": "/perks/:id",
      "handler": "perk.delete",
      "config": {
        "policies": []
      }
    }
  ]
}
